{"company_name": "Dubai World", "total_employees": 701}
{"company_name": "Dubai Industries & Exports", "total_employees": 22}
{"company_name": "Dubai First", "total_employees": 367}
{"company_name": "Dubai Islamic Insurance & Reinsurance Company", "total_employees": null}
{"company_name": "Dubai Luxury Property", "total_employees": 5}
{"company_name": "Dubai Money Coach", "total_employees": 1}
{"company_name": "Dubai Green Fund \u201cDGF\u201d", "total_employees": 14}
{"company_name": "Dubai Angel Investors - DAI", "total_employees": 33}
{"company_name": "ARK Capital Management (Dubai)", "total_employees": 15}
{"company_name": "Mondial (Dubai) LLC", "total_employees": 34}
{"company_name": "China Center Dubai Digital Park", "total_employees": 6}
{"company_name": "ALTUNKAYA GROUP OF COMPANIES- DUBAI", "total_employees": 24}
{"company_name": "Market Securities (Dubai) Limited", "total_employees": 30}
{"company_name": "Akbank (Dubai)", "total_employees": 10}
{"company_name": "DUBAI CRYPTO", "total_employees": 3}
{"company_name": "Dubai Financial Advice", "total_employees": 1}
{"company_name": "Gold Fund LLC - Dubai", "total_employees": 4}
{"company_name": "Access Dubai LLC", "total_employees": 3}
{"company_name": "Italian Incubator Dubai", "total_employees": 1}
{"company_name": "Chaturvedi Software House LLC, Dubai", "total_employees": 5}
{"company_name": "Goodwill World - Dubai Multi-Family Office", "total_employees": 15}
{"company_name": "Forward Investments (Dubai Electricity and Water Authority)", "total_employees": 3}
{"company_name": "Sell USDT In Dubai", "total_employees": 7}
{"company_name": "CHINAR GROUP OF COMPANIES, DUBAI, UAE", "total_employees": 1}
{"company_name": "Dubai Financial World", "total_employees": 2}
{"company_name": "GOLD TRUST DWC Dubai", "total_employees": 1}
{"company_name": "FFA Private Bank Dubai (Limited)", "total_employees": 20}
{"company_name": "Dubai Personal Finance", "total_employees": 1}
{"company_name": "RHDC INTERNATIONAL LLC - DUBAI", "total_employees": 9}
{"company_name": "Middle East Insurance Broker-Dubai", "total_employees": 1}
{"company_name": "Dubai Business Residence | \u062b\u0628\u062a \u0634\u0631\u06a9\u062a \u0648 \u0627\u0642\u0627\u0645\u062a \u062f\u0628\u06cc", "total_employees": 2}
{"company_name": "Czech Business Council in Dubai and Northern Emirates", "total_employees": 7}
{"company_name": "Dubai Lab", "total_employees": 5}
{"company_name": "Seif Group [El Ashrafia Investments] Dubai", "total_employees": 16}
{"company_name": "Business in Dubai", "total_employees": 1}
{"company_name": "NBN Dubai group", "total_employees": 16}
{"company_name": "Vita Wealth Management | Dubai", "total_employees": 8}
{"company_name": "Insurance_in_Dubai", "total_employees": 1}
{"company_name": "Dubai Global Home", "total_employees": 3}
{"company_name": "Easy Loan Dubai", "total_employees": 1}
{"company_name": "Vivere Dubai ", "total_employees": 1}
{"company_name": "Indonesia Trade Promotion Centre (ITPC) Dubai", "total_employees": 1}
{"company_name": "Investor Hub Dubai", "total_employees": 3}
{"company_name": "ROYAL INDEX LLC | Dubai", "total_employees": 64}
{"company_name": "Welldomo Mortgage Broker LLC", "total_employees": 1}
{"company_name": "Venture Capital Investments Dubai", "total_employees": 1}
{"company_name": "Pragma Group Dubai ", "total_employees": 5}
{"company_name": "Dubai Islamic Financial Services", "total_employees": 8}
{"company_name": "\u0645\u0631\u0643\u0632 \u062f\u0628\u064a \u0627\u0644\u062a\u062c\u0627\u0631\u064a", "total_employees": 10}
{"company_name": "Daily Desert Tourism Dubai", "total_employees": 3}
{"company_name": "Park Group Dubai", "total_employees": 16}
{"company_name": "Dubai Projects", "total_employees": 11}
{"company_name": "Dubai Waterfront Company", "total_employees": 2}
{"company_name": "Dubai Business International", "total_employees": 2}
{"company_name": "KeepSecure Dubai", "total_employees": 2}
{"company_name": "AL AIN AHLIA INSURANCE CO. (DUBAI BR.)", "total_employees": 7}
{"company_name": "Sell Bitcoin in Dubai", "total_employees": 1}
{"company_name": "Wallich & Matthes (Dubai) Limited", "total_employees": 2}
{"company_name": "Greycells LLC Dubai", "total_employees": 1}
{"company_name": "MEDCAPITAL LLC-FZ, DUBAI", "total_employees": 2}
{"company_name": "TA-TTOO", "total_employees": 3}
{"company_name": "Borse Dubai Limited", "total_employees": 2}
{"company_name": "Business Life Dubai", "total_employees": 2}
{"company_name": "Dubai Debt Solvers", "total_employees": 1}
{"company_name": "The Dubai Invest", "total_employees": 2}
{"company_name": "Multibilli Dubai LLC", "total_employees": 1}
{"company_name": "Finance Studio - Dubai", "total_employees": 2}
{"company_name": "COSMOS EXCHANGE DUBAI. All", "total_employees": 7}
{"company_name": "Abu Dhabi Growth Fund (ADG)", "total_employees": 7}
{"company_name": "Abu Dhabi Finance", "total_employees": 53}
{"company_name": "Industrial and Commercial Bank of China Limited - Abu Dhabi Branch", "total_employees": 15}
{"company_name": "Abu Dhabi Power Corporation", "total_employees": 13}
{"company_name": "AXA Gulf", "total_employees": 354}
{"company_name": "Recent job openings", "total_employees": null}
{"company_name": "Royal Avenue Investments", "total_employees": 17}
{"company_name": "TNC Group", "total_employees": 154}
{"company_name": "Recent job openings", "total_employees": null}
{"company_name": "Recent job openings", "total_employees": null}
{"company_name": "Products", "total_employees": null}
{"company_name": "Recent job openings", "total_employees": null}
{"company_name": "Daniel & Philip's Leaf (DPL Group)", "total_employees": 9}
{"company_name": "KEF Holdings", "total_employees": 141}
{"company_name": "U.S. Financial Advisory and Audit Firm (USFAAF) Inc.", "total_employees": 62}
{"company_name": "ANC Holdings LLC", "total_employees": 98}
{"company_name": "Revonence Technologies International", "total_employees": 7}
{"company_name": "Samanea Group", "total_employees": 272}
{"company_name": "Al Ghurair International Exchange", "total_employees": 97}
{"company_name": "Dubai World", "total_employees": 701}
{"company_name": "Recent job openings", "total_employees": null}
{"company_name": "Recent job openings", "total_employees": null}
{"company_name": "Recent job openings", "total_employees": null}
{"company_name": "Recent job openings", "total_employees": null}
{"company_name": "Products", "total_employees": null}
{"company_name": "Recent job openings", "total_employees": null}
{"company_name": "Recent job openings", "total_employees": null}
{"company_name": "Recent job openings", "total_employees": null}
{"company_name": "Recent job openings", "total_employees": null}
{"company_name": "Recent job openings", "total_employees": null}
{"company_name": "Recent job openings", "total_employees": null}
{"company_name": "Recent job openings", "total_employees": null}
{"company_name": "Recent job openings", "total_employees": null}
{"company_name": "Recent job openings", "total_employees": null}
{"company_name": "Past event", "total_employees": null}
{"company_name": "Recent job openings", "total_employees": null}
{"company_name": "Recent job openings", "total_employees": null}
{"company_name": "Recent job openings", "total_employees": null}
{"company_name": "Products", "total_employees": null}
{"company_name": "Products", "total_employees": null}
{"company_name": "Recent job openings", "total_employees": null}
{"company_name": "Recent job openings", "total_employees": null}
{"company_name": "Past event", "total_employees": null}
{"company_name": "Recent job openings", "total_employees": null}
{"company_name": "Past events", "total_employees": null}
{"company_name": "Recent job openings", "total_employees": null}
